electromake/usb_thermometer/__init__.py
electromake/usb_thermometer/example1.py
electromake/usb_thermometer/example2.py
electromake/usb_thermometer/example3.py
electromake/usb_thermometer/example4.py
electromake/usb_thermometer/exceptions.py
electromake/usb_thermometer/sensors.py
electromake/usb_thermometer/thermometer.py
electromake/usb_thermometer/utils.py
electromake_usb_thermometer-0.1.0.dist-info/METADATA
electromake_usb_thermometer-0.1.0.dist-info/WHEEL
electromake_usb_thermometer-0.1.0.dist-info/top_level.txt
electromake_usb_thermometer-0.1.0.dist-info/RECORD
