Metadata-Version: 2.2
Name: electromake-usb-thermometer
Version: 0.1.0
Summary: USB Thermometer Library
Author: Electromake
Requires-Python: >=3.6
